tmpk/__init__.py
tmpk/__main__.py
tmpk/tmpk.py
tmpk-1.1.1.dist-info/LICENSE
tmpk-1.1.1.dist-info/METADATA
tmpk-1.1.1.dist-info/WHEEL
tmpk-1.1.1.dist-info/entry_points.txt
tmpk-1.1.1.dist-info/top_level.txt
tmpk-1.1.1.dist-info/RECORD
